Metadata-Version: 2.1
Name: FlaskSqaured
Version: 0.1
Summary: An easier and more simple version of flask.
Home-page: https://github.com/WhineyMonkey10/easyflask
Download-URL: https://github.com/WhineyMonkey10/FlaskSqaured/archive/refs/tags/v.0.1.3.tar.gz
Author: WhMonkey
Author-email: no-reply@no-reply.com
License: MIT
Keywords: FLASK,WEBSITE,EASY
Classifier: Development Status :: 3 - Alpha
Classifier: Intended Audience :: Developers
Classifier: Topic :: Software Development :: Build Tools
Classifier: License :: OSI Approved :: MIT License
Classifier: Programming Language :: Python :: 3
Classifier: Programming Language :: Python :: 3.4
Classifier: Programming Language :: Python :: 3.5
Classifier: Programming Language :: Python :: 3.6
License-File: LICENSE.txt
